setup.py
pywebview_unofficial_osx_patched.egg-info/PKG-INFO
pywebview_unofficial_osx_patched.egg-info/SOURCES.txt
pywebview_unofficial_osx_patched.egg-info/dependency_links.txt
pywebview_unofficial_osx_patched.egg-info/requires.txt
pywebview_unofficial_osx_patched.egg-info/top_level.txt
webview/__init__.py
webview/cocoa.py
webview/gtk.py
webview/qt.py
webview/win32.py
webview/win32_gen.py