Metadata-Version: 1.1
Name: pywebview-unofficial-osx-patched
Version: 0.8.4
Summary: A cross-platform lightweight native wrapper around a web view component
Home-page: http://github.com/r0x0r/pywebview
Author: Roman Sirokov
Author-email: roman@flowrl.com
License: New BSD license
Download-URL: https://github.com/r0x0r/pywebview/archive/0.8.4.tar.gz
Keywords: gui,webkit,html,web
Platform: UNKNOWN
Classifier: Intended Audience :: Developers
Classifier: License :: OSI Approved :: BSD License
Classifier: Operating System :: OS Independent
Classifier: Environment :: MacOS X
Classifier: Environment :: Win32 (MS Windows)
Classifier: Environment :: X11 Applications :: GTK
Classifier: Environment :: X11 Applications :: Qt
Classifier: Programming Language :: Python
Classifier: Programming Language :: Python :: 2
Classifier: Programming Language :: Python :: 2.7
Classifier: Programming Language :: Python :: 3
Classifier: Programming Language :: Python :: 3.4
Classifier: Topic :: Software Development :: Libraries :: Application Frameworks
Classifier: Topic :: Software Development :: Libraries :: Python Modules
Classifier: Topic :: Software Development :: User Interfaces
